README.md
setup.cfg
setup.py
fisherman/__init__.py
fisherman/exceptions.py
fisherman/main.py
fisherman.egg-info/PKG-INFO
fisherman.egg-info/SOURCES.txt
fisherman.egg-info/dependency_links.txt
fisherman.egg-info/entry_points.txt
fisherman.egg-info/requires.txt
fisherman.egg-info/top_level.txt
fisherman/services/__init__.py
fisherman/services/apility.py
fisherman/services/emailrep.py
fisherman/utils/__init__.py
fisherman/utils/colors.py