Metadata-Version: 2.1
Name: fisherman
Version: 1.0.1
Summary: A tool for looking up an email address's reputation on EmailRep and Apility without API keys
Home-page: https://github.com/0xedward/fisherman
Author: Edward
Author-email: 14011954+0xedward@users.noreply.github.com
License: MIT
Download-URL: https://github.com/0xedward/fisherman/archive/1.0.0.tar.gz
Keywords: security,phishing
Platform: UNKNOWN
Classifier: Topic :: Security
Classifier: Programming Language :: Python :: 3
Classifier: License :: OSI Approved :: MIT License
Classifier: Operating System :: OS Independent
Classifier: Natural Language :: English
